Workbook

Sheet Données
A1: Mois | B1: Mois_date | C1: Business_Unit_Code | D1: Business_Unit | E1: Centre_Cout_Code | F1: Centre_Cout | G1: Nature_Depense | H1: Budget_EUR | I1: Reel_EUR | J1: Écart € | K1: Écart % | L1: Significatif
A2: 2025-01 | B2: 45658 | C2: BU01 | D2: CONSTRUCTION FRANCE | E2: CC1001 | F2: IT | G2: LOGICIELS | H2: 6335.71 | I2: 7373.09 | J2: 1037.38 | K2: 16.37354 | L2: Non significatif
A3: 2025-01 | B3: 45658 | C3: BU01 | D3: CONSTRUCTION FRANCE | E3: CC1001 | F3: IT | G3: PRESTATIONS EXTERNES | H3: 10702.77 | I3: 11211.76 | J3: 508.99 | K3: 4.7556847 | L3: Non significatif
A4: 2025-01 | B4: 45658 | C4: BU01 | D4: CONSTRUCTION FRANCE | E4: CC1001 | F4: IT | G4: SALAIRES | H4: 15185 | I4: 13688.95 | J4: -1496.05 | K4: -9.8521567 | L4: Non significatif
A5: 2025-01 | B5: 45658 | C5: BU01 | D5: CONSTRUCTION FRANCE | E5: CC1001 | F5: IT | G5: MATÉRIEL | H5: 5493.95 | I5: 6240.24 | J5: 746.29 | K5: 13.583851 | L5: Non significatif
A6: 2025-01 | B6: 45658 | C6: BU01 | D6: CONSTRUCTION FRANCE | E6: CC1001 | F6: IT | G6: DÉPLACEMENTS | H6: 3887.34 | I6: 4212.57 | J6: 325.23 | K6: 8.3663894 | L6: Non significatif
A7: 2025-01 | B7: 45658 | C7: BU01 | D7: CONSTRUCTION FRANCE | E7: CC1001 | F7: IT | G7: LOGICIEL | H7: 4574.1 | I7: 5352.02 | J7: 777.92 | K7: 17.007061 | L7: Non significatif
A8: 2025-01 | B8: 45658 | C8: BU01 | D8: CONSTRUCTION FRANCE | E8: CC1002 | F8: RESSOURCES HUMAINES | G8: RESSOURCES HUMAINES | H8: 8121.53 | I8: 7472.39 | J8: -649.14 | K8: -7.9928289 | L8: Non significatif
A9: 2025-01 | B9: 45658 | C9: BU01 | D9: CONSTRUCTION FRANCE | E9: CC1002 | F9: RESSOURCES HUMAINES | G9: PRESTATIONS EXTERNES | H9: 7731.85 | I9: 7040.04 | J9: -691.81 | K9: -8.9475352 | L9: Non significatif
A10: 2025-01 | B10: 45658 | C10: BU01 | D10: CONSTRUCTION FRANCE | E10: CC1002 | F10: RESSOURCES HUMAINES | G10: SALAIRES | H10: 16785.82 | I10: 17174.74 | J10: 388.92 | K10: 2.3169556 | L10: Non significatif
A11: 2025-01 | B11: 45658 | C11: BU01 | D11: CONSTRUCTION FRANCE | E11: CC1002 | F11: RESSOURCES HUMAINES | G11: MATÉRIEL | H11: 7064.17 | I11: 6683.45 | J11: -380.72 | K11: -5.3894513 | L11: Non significatif
A12: 2025-01 | B12: 45658 | C12: BU01 | D12: CONSTRUCTION FRANCE | E12: CC1002 | F12: RESSOURCES HUMAINES | G12: DÉPLACEMENTS | H12: 3909.89 | I12: 3503.39 | J12: -406.5 | K12: -10.396712 | L12: Non significatif
A13: 2025-01 | B13: 45658 | C13: BU01 | D13: CONSTRUCTION FRANCE | E13: CC1002 | F13: RESSOURCES HUMAINES | G13: ÉNERGIE | H13: 5551.72 | I13: 5390.16 | J13: -161.56 | K13: -2.9100891 | L13: Non significatif
... A865: 2025-12 | B865: 45992 | C865: BU04 | D865: INFRASTRUCTURES | E865: CC4003 | F865: FINANCE | G865: ÉNERGIE | H865: 6333.92 | I865: 7467.12 | J865: 1133.2 | K865: 17.890974 | L865: Non significatif

Sheet synthèse des anomalies
A1: Indicateur | B1: Resultat
A2: Nombre total de lignes | B2: =COUNTA(Données!G2:G8309) -> 864
A3: Nombre d'écarts significatifs | B3: =COUNTIF(Données!L:L,"Significatif") -> 3
A4: Nombre d'écarts positifs | B4: =COUNTIF(Données!J:J,">0") -> 490
A5: Nombre d'écarts négatifs | B5: =COUNTIF(Données!J:J,"<0") -> 374
A6: Écart positif maximum | B6: =MAX(Données!J:J) -> 15500
A7: Écart négatif maximum | B7: =MIN(Données!J:J) -> -38036.01

Sheet Top_Ecarts
A1: Mois | B1: Business Unit | C1: Centre de coût | D1: Nature | E1: Budget | F1: Réel | G1: Écart € | H1: Écart % | I1: Significatif
A2: {=_xlfn._xlws.FILTER(Données!A2:I8309,(Données!J2:J8309>10000)*(Données!K2:K8309>10%),"Aucun écart significatif")} -> 2025-05 | B2: 45778 | C2: BU01 | D2: CONSTRUCTION FRANCE | E2: CC1001 | F2: IT | G2: LOGICIELS | H2: 5448.59 | I2: 20448.59
A3: 2025-10 | B3: 45931 | C3: BU04 | D3: INFRASTRUCTURES | E3: CC4002 | F3: MAINTENANCE | G3: ÉNERGIE | H3: 150000 | I3: 165500

Sheet Drilldown_Business_Unit
A1: Business Unit | B1: Budget total | C1: Réel total | D1: Écart € | E1: Écart %
A2: BU01 | B2: =SUMIFS(Données!$H:$H,Données!$C:$C,A2) -> 1850480.6 | C2: =SUMIFS(Données!$I:$I,Données!$C:$C,A2) -> 1897131 | D2: =C2-B2 -> 46650.49 | E2: =D2/B2 -> 0.025209932
A3: BU02 | B3: =SUMIFS(Données!$H:$H,Données!$C:$C,A3) -> 1884824.9 | C3: =SUMIFS(Données!$I:$I,Données!$C:$C,A3) -> 1872970.7 | D3: =C3-B3 -> -11854.192 | E3: =D3/B3 -> -0.0062892806
A4: BU03 | B4: =SUMIFS(Données!$H:$H,Données!$C:$C,A4) -> 1928957.5 | C4: =SUMIFS(Données!$I:$I,Données!$C:$C,A4) -> 1957048.4 | D4: =C4-B4 -> 28090.874 | E4: =D4/B4 -> 0.014562723
A5: BU04 | B5: =SUMIFS(Données!$H:$H,Données!$C:$C,A5) -> 2001965.6 | C5: =SUMIFS(Données!$I:$I,Données!$C:$C,A5) -> 2044165.3 | D5: =C5-B5 -> 42199.64 | E5: =D5/B5 -> 0.021079103

Sheet Drilldown_CC
A1: Centre de coûts | B1: Budget total | C1: Réel total | D1: Écart € | E1: Écart %
A2: CC1001 | B2: =SUMIFS(Données!H:H,Données!C:C,"BU01",Données!E:E,A2) -> 615990.68 | C2: =SUMIFS(Données!I:I,Données!C:C,"BU01",Données!E:E,A2) -> 641245.35 | D2: =C2-B2 -> 25254.67 | E2: =D2/B2 -> 0.040998461
A3: CC1002 | B3: =SUMIFS(Données!H:H,Données!C:C,"BU01",Données!E:E,A3) -> 602694.34 | C3: =SUMIFS(Données!I:I,Données!C:C,"BU01",Données!E:E,A3) -> 622010.67 | D3: =C3-B3 -> 19316.33 | E3: =D3/B3 -> 0.032049961
A4: CC1003 | B4: =SUMIFS(Données!H:H,Données!C:C,"BU01",Données!E:E,A4) -> 631795.54 | C4: =SUMIFS(Données!I:I,Données!C:C,"BU01",Données!E:E,A4) -> 633875.03 | D4: =C4-B4 -> 2079.49 | E4: =D4/B4 -> 0.0032913971

Sheet kpi
A1: Budget total | B1: Réel total | C1: Ecart total € | D1: Ecart total % | E1: Nb Centre de couts significatif | F1: Nb BU avec Ecart significatif
A2: =SUM(Données!H2:H865) -> 7666228.6 | B2: =SUM(Données!I2:I865) -> 7771315.4 | C2: =B2-A2 -> 105086.81 | D2: =C2/A2*100 -> 1.3707759 | E2: =COUNTIF(Données!L2:L865,"Significatif") -> 2 | F2: {=COUNTA(_xlfn.UNIQUE(_xlfn._xlws.FILTER(Données!B2:B865,Données!L2:L865="Significatif")))} -> 2

Sheet Drilldown_BU
A1: Business Unit | B1: Budget total | C1: Réel total | D1: Écart € | E1: Écart %
A2: Construction France | B2: =SUMIF(Données!D:D,A2,Données!H:H) -> 1850480.6 | C2: =SUMIF(Données!D:D,A2,Données!I:I) -> 1897131 | D2: =C2-B2 -> 46650.49 | E2: =D2/B2*100 -> 2.5209932
A3: Construction UK | B3: =SUMIF(Données!D:D,A3,Données!H:H) -> 1884824.9 | C3: =SUMIF(Données!D:D,A3,Données!I:I) -> 1872970.7 | D3: =C3-B3 -> -11854.192 | E3: =D3/B3*100 -> -0.62892806
A4: Energie | B4: =SUMIF(Données!D:D,A4,Données!H:H) -> 1928957.5 | C4: =SUMIF(Données!D:D,A4,Données!I:I) -> 1957048.4 | D4: =C4-B4 -> 28090.874 | E4: =D4/B4*100 -> 1.4562723
A5: Infrastructures | B5: =SUMIF(Données!D:D,A5,Données!H:H) -> 2001965.6 | C5: =SUMIF(Données!D:D,A5,Données!I:I) -> 2044165.3 | D5: =C5-B5 -> 42199.64 | E5: =D5/B5*100 -> 2.1079103

Sheet Drilldown_Nature
A1: Nature de dépense | B1: Budget total | C1: Réel total | D1: Écart € | E1: Écart %
A2: LOGICIELS | B2: =SUMIFS(Données!$H:$H,Données!$G:$G,A2) -> 969766.57 | C2: =SUMIFS(Données!$I:$I,Données!$G:$G,A2) -> 993952.69 | D2: =C2-B2 -> 24186.12 | E2: =IF(B2=0,0,D2/B2) -> 0.024940146
A3: PRESTATIONS EXTERNES | B3: =SUMIFS(Données!$H:$H,Données!$G:$G,A3) -> 1339531.8 | C3: =SUMIFS(Données!$I:$I,Données!$G:$G,A3) -> 1375008.8 | D3: =C3-B3 -> 35477.004 | E3: =IF(B3=0,0,D3/B3) -> 0.02648463
A4: SALAIRES | B4: =SUMIFS(Données!$H:$H,Données!$G:$G,A4) -> 2684693.9 | C4: =SUMIFS(Données!$I:$I,Données!$G:$G,A4) -> 2703446.2 | D4: =C4-B4 -> 18752.348 | E4: =IF(B4=0,0,D4/B4) -> 0.0069849109
A5: MATERIEL | B5: =SUMIFS(Données!$H:$H,Données!$G:$G,A5) -> 0 | C5: =SUMIFS(Données!$I:$I,Données!$G:$G,A5) -> 0 | D5: =C5-B5 -> 0 | E5: =IF(B5=0,0,D5/B5) -> 0
A6: DÉPLACEMENTS | B6: =SUMIFS(Données!$H:$H,Données!$G:$G,A6) -> 533804.44 | C6: =SUMIFS(Données!$I:$I,Données!$G:$G,A6) -> 544567.71 | D6: =C6-B6 -> 10763.27 | E6: =IF(B6=0,0,D6/B6) -> 0.02016332
A7: ÉNERGIE | B7: =SUMIFS(Données!$H:$H,Données!$G:$G,A7) -> 1054339.6 | C7: =SUMIFS(Données!$I:$I,Données!$G:$G,A7) -> 1043261.5 | D7: =C7-B7 -> -11078.01 | E7: =IF(B7=0,0,D7/B7) -> -0.010507061

Sheet Drilldown_Centre_Cout
A1: Centre de coût | B1: Budget total | C1: Réel total | D1: Écart € | E1: Écart %
A2: IT | B2: =SUMIFS(Données!$H:$H,Données!$F:$F,A2) -> 2522350.2 | C2: =SUMIFS(Données!$I:$I,Données!$F:$F,A2) -> 2591869.7 | D2: =C2-B2 -> 69519.464 | E2: =D2/B2 -> 0.027561385
A3: RESSOURCES HUMAINES | B3: =SUMIFS(Données!$H:$H,Données!$F:$F,A3) -> 1280801.6 | C3: =SUMIFS(Données!$I:$I,Données!$F:$F,A3) -> 1272213.7 | D3: =C3-B3 -> -8587.9024 | E3: =D3/B3 -> -0.0067050997
A4: FINANCE | B4: =SUMIFS(Données!$H:$H,Données!$F:$F,A4) -> 2463747.1 | C4: =SUMIFS(Données!$I:$I,Données!$F:$F,A4) -> 2491876.6 | D4: =C4-B4 -> 28129.44 | E4: =D4/B4 -> 0.011417341
A5: MAINTENANCE | B5: =SUMIFS(Données!$H:$H,Données!$F:$F,A5) -> 1399329.6 | C5: =SUMIFS(Données!$I:$I,Données!$F:$F,A5) -> 1415355.5 | D5: =C5-B5 -> 16025.81 | E5: =D5/B5 -> 0.011452491

Sheet Drilldown_Mois
A1: Mois | B1: Budget total | C1: Réel total | D1: Écart € | E1: Écart %
A2: 45658 | B2: =SUMIFS(Données!$H:$H,Données!$B:$B,A2) -> 656886.42 | C2: =SUMIFS(Données!$I:$I,Données!$B:$B,A2) -> 619259.46 | D2: =C2-B2 -> -37626.96 | E2: =D2/B2 -> -0.05728077
A3: 45689 | B3: =SUMIFS(Données!$H:$H,Données!$B:$B,A3) -> 633140.03 | C3: =SUMIFS(Données!$I:$I,Données!$B:$B,A3) -> 640830.64 | D3: =C3-B3 -> 7690.6144 | E3: =D3/B3 -> 0.012146783
A4: 45717 | B4: =SUMIFS(Données!$H:$H,Données!$B:$B,A4) -> 631857.21 | C4: =SUMIFS(Données!$I:$I,Données!$B:$B,A4) -> 643389.52 | D4: =C4-B4 -> 11532.31 | E4: =D4/B4 -> 0.018251449
A5: 45748 | B5: =SUMIFS(Données!$H:$H,Données!$B:$B,A5) -> 634922.15 | C5: =SUMIFS(Données!$I:$I,Données!$B:$B,A5) -> 655198.27 | D5: =C5-B5 -> 20276.12 | E5: =D5/B5 -> 0.031934813
A6: 45778 | B6: =SUMIFS(Données!$H:$H,Données!$B:$B,A6) -> 580334.45 | C6: =SUMIFS(Données!$I:$I,Données!$B:$B,A6) -> 597785.33 | D6: =C6-B6 -> 17450.88 | E6: =D6/B6 -> 0.030070384
A7: 45809 | B7: =SUMIFS(Données!$H:$H,Données!$B:$B,A7) -> 600622.15 | C7: =SUMIFS(Données!$I:$I,Données!$B:$B,A7) -> 621734.94 | D7: =C7-B7 -> 21112.791 | E7: =D7/B7 -> 0.035151536
A8: 45839 | B8: =SUMIFS(Données!$H:$H,Données!$B:$B,A8) -> 609819.28 | C8: =SUMIFS(Données!$I:$I,Données!$B:$B,A8) -> 620455.14 | D8: =C8-B8 -> 10635.86 | E8: =D8/B8 -> 0.017441003
A9: 45870 | B9: =SUMIFS(Données!$H:$H,Données!$B:$B,A9) -> 659535 | C9: =SUMIFS(Données!$I:$I,Données!$B:$B,A9) -> 659853.53 | D9: =C9-B9 -> 318.5332 | E9: =D9/B9 -> 0.00048296633
A10: 45901 | B10: =SUMIFS(Données!$H:$H,Données!$B:$B,A10) -> 618992.06 | C10: =SUMIFS(Données!$I:$I,Données!$B:$B,A10) -> 626150.31 | D10: =C10-B10 -> 7158.2528 | E10: =D10/B10 -> 0.011564369
A11: 45931 | B11: =SUMIFS(Données!$H:$H,Données!$B:$B,A11) -> 776164.08 | C11: =SUMIFS(Données!$I:$I,Données!$B:$B,A11) -> 804217.56 | D11: =C11-B11 -> 28053.48 | E11: =D11/B11 -> 0.036143749
A12: 45962 | B12: =SUMIFS(Données!$H:$H,Données!$B:$B,A12) -> 651468.39 | C12: =SUMIFS(Données!$I:$I,Données!$B:$B,A12) -> 654875.19 | D12: =C12-B12 -> 3406.8 | E12: =D12/B12 -> 0.0052294172
A13: 45992 | B13: =SUMIFS(Données!$H:$H,Données!$B:$B,A13) -> 612487.33 | C13: =SUMIFS(Données!$I:$I,Données!$B:$B,A13) -> 627565.46 | D13: =C13-B13 -> 15078.13 | E13: =D13/B13 -> 0.024617864
